ai_commiter/__init__.py
ai_commiter/config.py
ai_commiter/git_commit_ai.py
ai_commiter-1.2.4.dist-info/licenses/LICENSE
ai_commiter-1.2.4.dist-info/METADATA
ai_commiter-1.2.4.dist-info/WHEEL
ai_commiter-1.2.4.dist-info/entry_points.txt
ai_commiter-1.2.4.dist-info/top_level.txt
ai_commiter-1.2.4.dist-info/RECORD
