Metadata-Version: 2.4
Name: ai-commiter
Version: 1.2.4
Summary: AI-powered Git commit message generator with multi-language support
Author: kim donghun
License: MIT
Project-URL: Homepage, https://github.com/hunknownn/ai-commiter
Project-URL: Issues, https://github.com/hunknownn/ai-commiter/issues
Classifier: Programming Language :: Python :: 3
Classifier: License :: OSI Approved :: MIT License
Classifier: Operating System :: OS Independent
Requires-Python: >=3.7
License-File: LICENSE
Requires-Dist: gitpython>=3.1.31
Requires-Dist: openai>=0.27.8
Requires-Dist: langchain>=0.0.267
Requires-Dist: langchain-openai>=0.0.1
Requires-Dist: python-dotenv>=1.0.0
Dynamic: license-file
